pulumi_bytepluscc/__init__.py
pulumi_bytepluscc/_inputs.py
pulumi_bytepluscc/_utilities.py
pulumi_bytepluscc/provider.py
pulumi_bytepluscc/pulumi-plugin.json
pulumi_bytepluscc/py.typed
pulumi_bytepluscc/alb/__init__.py
pulumi_bytepluscc/alb/_inputs.py
pulumi_bytepluscc/alb/acl.py
pulumi_bytepluscc/alb/certificate.py
pulumi_bytepluscc/alb/get_acl.py
pulumi_bytepluscc/alb/get_acls.py
pulumi_bytepluscc/alb/get_certificate.py
pulumi_bytepluscc/alb/get_certificates.py
pulumi_bytepluscc/alb/get_listener.py
pulumi_bytepluscc/alb/get_listeners.py
pulumi_bytepluscc/alb/get_load_balancer.py
pulumi_bytepluscc/alb/get_load_balancers.py
pulumi_bytepluscc/alb/get_server_group.py
pulumi_bytepluscc/alb/get_server_groups.py
pulumi_bytepluscc/alb/listener.py
pulumi_bytepluscc/alb/load_balancer.py
pulumi_bytepluscc/alb/outputs.py
pulumi_bytepluscc/alb/server_group.py
pulumi_bytepluscc/apig/__init__.py
pulumi_bytepluscc/apig/_inputs.py
pulumi_bytepluscc/apig/custom_domain.py
pulumi_bytepluscc/apig/gateway.py
pulumi_bytepluscc/apig/gateway_service.py
pulumi_bytepluscc/apig/get_custom_domain.py
pulumi_bytepluscc/apig/get_custom_domains.py
pulumi_bytepluscc/apig/get_gateway.py
pulumi_bytepluscc/apig/get_gateway_service.py
pulumi_bytepluscc/apig/get_gateway_services.py
pulumi_bytepluscc/apig/get_gateways.py
pulumi_bytepluscc/apig/get_upstream.py
pulumi_bytepluscc/apig/get_upstream_source.py
pulumi_bytepluscc/apig/get_upstream_sources.py
pulumi_bytepluscc/apig/get_upstreams.py
pulumi_bytepluscc/apig/outputs.py
pulumi_bytepluscc/apig/upstream.py
pulumi_bytepluscc/apig/upstream_source.py
pulumi_bytepluscc/autoscaling/__init__.py
pulumi_bytepluscc/autoscaling/_inputs.py
pulumi_bytepluscc/autoscaling/get_scaling_configuration.py
pulumi_bytepluscc/autoscaling/get_scaling_configurations.py
pulumi_bytepluscc/autoscaling/get_scaling_group.py
pulumi_bytepluscc/autoscaling/get_scaling_groups.py
pulumi_bytepluscc/autoscaling/outputs.py
pulumi_bytepluscc/autoscaling/scaling_configuration.py
pulumi_bytepluscc-0.0.12.dist-info/METADATA
pulumi_bytepluscc-0.0.12.dist-info/WHEEL
pulumi_bytepluscc-0.0.12.dist-info/top_level.txt
pulumi_bytepluscc-0.0.12.dist-info/RECORD
