Metadata-Version: 2.4
Name: pulumi_bytepluscc
Version: 0.0.12
Summary: A Pulumi package to safely use byteplus Resource in Pulumi programs.
Home-page: https://github.com/byteplus-sdk/pulumi-bytepluscc
License: MPL-2.0
Project-URL: Repository, https://github.com/byteplus-sdk/pulumi-bytepluscc
Keywords: byteplus bytepluscc category/cloud
Requires-Python: >=3.9
Requires-Dist: parver>=0.2.1
Requires-Dist: pulumi<4.0.0,>=3.165.0
Requires-Dist: semver>=2.8.1
Requires-Dist: typing-extensions<5,>=4.11; python_version < "3.11"
Dynamic: description
Dynamic: description-content-type
Dynamic: home-page
Dynamic: keywords
Dynamic: license
Dynamic: project-url
Dynamic: requires-dist
Dynamic: requires-python
Dynamic: summary
